conqueror/__init__.py
conqueror/__main__.py
conqueror/app.py
conqueror/cassandra.py
conqueror/run.py
conqueror/cities/__init__.py
conqueror/endpoints/__init__.py
conqueror/endpoints/add_account.py
conqueror/endpoints/add_business.py
conqueror/endpoints/add_review.py
conqueror/endpoints/view_business.py
conqueror/endpoints/view_cities.py
conqueror/endpoints/view_messages.py
conqueror/msg_generator/__init__.py
conqueror/msg_generator/definitions.py
conqueror/msg_generator/messages.py
conqueror/scraper/__init__.py
conqueror/scraper/__main__.py
conqueror/scraper/base_yandex.py
conqueror/scraper/data_importer.py
conqueror/scraper/data_reader.py
conqueror/scraper/get_object_types.py
conqueror/scraper/orders_obtainer.py
conqueror/scraper/pulse_coordinator.py
conqueror/scraper/scrap_yandex.py
conqueror/scraper/yandex_api_schema.py
conqueror/utils/__init__.py
conqueror/utils/geom2d.py
conqueror/utils/point_obtain.py
yandex_conqueror-1.3.dist-info/LICENSE
yandex_conqueror-1.3.dist-info/METADATA
yandex_conqueror-1.3.dist-info/WHEEL
yandex_conqueror-1.3.dist-info/top_level.txt
yandex_conqueror-1.3.dist-info/RECORD
