Metadata-Version: 2.1
Name: yandex-conqueror
Version: 1.3
Summary: An opinion adder to inform the Russian public about what's going on in Ukraine
Home-page: https://git.dms-serwis.com.pl/yandex-conqueror/conqueror
Author: Piotr Maślanka
Author-email: pmaslanka@smok.co
License: UNKNOWN
Keywords: spam bot,bot,spam,yandex,russia,putin
Platform: UNKNOWN
Requires-Python: !=2.7.*,!=3.0.*,!=3.1.*,!=3.2.*,!=3.3.*,!=3.4.*
Requires-Dist: requests
Requires-Dist: selenium
Requires-Dist: webdriver-manager
Requires-Dist: satella
